oarepo_published_service/__init__.py
oarepo_published_service/ext.py
oarepo_published_service/ext_config.py
oarepo_published_service/proxies.py
oarepo_published_service/records/__init__.py
oarepo_published_service/services/__init__.py
oarepo_published_service/services/config.py
oarepo_published_service/services/service.py
oarepo_published_service/services/records/__init__.py
oarepo_published_service/services/records/components/__init__.py
oarepo_published_service/services/records/components/bucket.py
oarepo_published_service/services/records/components/pid_register.py
oarepo_published_service-1.0.3.dist-info/LICENSE
oarepo_published_service-1.0.3.dist-info/METADATA
oarepo_published_service-1.0.3.dist-info/WHEEL
oarepo_published_service-1.0.3.dist-info/entry_points.txt
oarepo_published_service-1.0.3.dist-info/top_level.txt
oarepo_published_service-1.0.3.dist-info/RECORD
